Workbook

Sheet Feature Inventory
A1: Feature ID | B1: Module | C1: Stage | D1: Feature | E1: What It Does | F1: Phase | G1: Priority (MoSCoW) | H1: Complexity (S/M/L) | I1: Effort Estimate (Person-Days) | J1: Effort Estimate (Person-Hours) | K1: Effort Estimate w/ Claude AI Assistance (Person-Days) | L1: Effort Estimate w/ Claude AI Assistance (Person-Hours) | M1: Notes
D2: Authentication & Authorization | E2: Login, AD authentication and User access matrix | F2: 1 | H2: S | J2: 80 | L2: 56
D3: Notification Module | E3: Email notification, In App notification | F3: 1 | H3: L | J3: 160 | L3: 120
A4: F-001 | B4: Module 1 - Procurement | C4: Define & Plan | D4: Create Project | E4: Register a new vehicle programme / project so downstream parts, suppliers and cost records have somewhere to attach. | F4: 1 | G4: Must | H4: M | I4: 5 | J4: 40 | K4: 3 | L4: 24
A5: F-002 | B5: Module 1 - Procurement | C5: Define & Plan | D5: Upload BOM & Part List | E5: Bulk-load the parts list and BOM lines for a project ahead of sourcing. | F5: 1 | G5: Must | H5: L | I5: 12 | J5: 96 | K5: 7 | L5: 56
A6: F-003 | B6: Module 1 - Procurement | C6: Define & Plan | D6: Maintain Master Data (Project, Part, Supplier, Commodity, FX) | E6: Single screen/entry point for all core masters used across the platform. | F6: 1 | G6: Must | H6: L | I6: 15 | J6: 120 | K6: 8 | L6: 64
A7: F-004 | B7: Module 1 - Procurement | C7: Define & Plan | D7: Define Commodity & Exchange Rate | E7: Set up commodity items and FX rates that CBD and pricing calculations will reference. | F7: 1 | G7: Must | H7: M | I7: 6 | J7: 48 | K7: 3 | L7: 24
A8: F-005 | B8: Module 1 - Procurement | C8: Define & Plan | D8: Define Milestones & Targets | E8: Set the project-level milestone plan (dates/targets) that SRM and Technical Change later track against. | F8: 1 | G8: Must | H8: L | I8: 10 | J8: 80 | K8: 7 | L8: 56
A9: F-006 | B9: Module 1 - Procurement | C9: Source & Nominate | D9: Import Sourcing Report (EBON+) | E9: Ingest the Sourcing Report (Excel, 85 columns) for decided sourcing at defined intervals; system parses and updates the database. | F9: 1 | G9: Must | H9: L | I9: 18 | J9: 144 | K9: 11 | L9: 88
A10: F-007 | B10: Module 1 - Procurement | C10: Source & Nominate | D10: RFQ Management | E10: Track Request-for-Quotation issuance to shortlisted suppliers. | F10: 1 | G10: Should | H10: M | I10: 7 | J10: 56 | K10: 5 | L10: 40
A11: F-008 | B11: Module 1 - Procurement | C11: Source & Nominate | D11: Supplier Quotations | E11: Capture supplier-submitted quotes against an RFQ. | F11: 1 | G11: Should | H11: M | I11: 6 | J11: 48 | K11: 4 | L11: 32
A12: F-009 | B12: Module 1 - Procurement | C12: Source & Nominate | D12: Supplier Comparison | E12: Side-by-side comparison view of competing supplier quotes. | F12: 1 | G12: Should | H12: S | I12: 4 | J12: 32 | K12: 2 | L12: 16
A13: F-010 | B13: Module 1 - Procurement | C13: Source & Nominate | D13: Supplier Nomination | E13: Formally nominate the winning supplier for a part. | F13: 1 | G13: Must | H13: M | I13: 5 | J13: 40 | K13: 3 | L13: 24
A14: F-011 | B14: Module 1 - Procurement | C14: Source & Nominate | D14: Commercial Negotiation | E14: Record negotiation rounds and final agreed terms before CBD lock. | F14: 1 | G14: Must | H14: M | I14: 6 | J14: 48 | K14: 4 | L14: 32
A15: F-012 | B15: Module 1 - Procurement | C15: Commercial Management | D15: Cost Breakdown (CBD) | E15: Capture the full cost structure per part: quantity/car, weights (Steel/Alu/Cu/Pb/Precious, gross+net), import content & FX, VSI, Target, D&D amortisation. | F15: 1 | G15: Must | H15: L | I15: 18 | J15: 144 | K15: 13 | L15: 104
... A151: F-148 | B151: Cross-Cutting Platform | C151: Platform Services | D151: Annual AI / Software Version Upgrade | E151: Yearly upgrade of the AI model / software version at no additional cost, per the RFQ commercial requirement. | F151: 3 | G151: Must | H151: M | I151: 5 | J151: 40 | K151: 5 | L151: 40
J152: =SUM(J2:J151) -> 9872 | K152: =SUM(K2:K151) -> 793 | L152: =SUM(L2:L151) -> 6560

Sheet Summary
A1: Module | B1: Total Features | C1: RFQ Traceability | D1: Scope Review Flags | E1: Must | F1: Should | G1: Could | H1: Phase 1 | I1: Phase 2 | J1: Phase 3 | K1: Small | L1: Medium | M1: Large
A2: Module 1 - Procurement | B2: =COUNTIF('Feature Inventory'!B:B,A2) -> 40 | C2: Not captured | D2: 5 | E2: =COUNTIFS('Feature Inventory'!B:B,A2,'Feature Inventory'!G:G,"Must") -> 32 | F2: =COUNTIFS('Feature Inventory'!B:B,A2,'Feature Inventory'!G:G,"Should") -> 6 | G2: =COUNTIFS('Feature Inventory'!B:B,A2,'Feature Inventory'!G:G,"Could") -> 2 | H2: =COUNTIFS('Feature Inventory'!B:B,A2,'Feature Inventory'!F:F,"1") -> 39 | I2: =COUNTIFS('Feature Inventory'!B:B,A2,'Feature Inventory'!F:F,"2") -> 0 | J2: =COUNTIFS('Feature Inventory'!B:B,A2,'Feature Inventory'!F:F,"3") -> 1 | K2: =COUNTIFS('Feature Inventory'!B:B,A2,'Feature Inventory'!H:H,"S") -> 6 | L2: =COUNTIFS('Feature Inventory'!B:B,A2,'Feature Inventory'!H:H,"M") -> 22 | M2: =COUNTIFS('Feature Inventory'!B:B,A2,'Feature Inventory'!H:H,"L") -> 12
A3: Procurement Orders | B3: =COUNTIF('Feature Inventory'!B:B,A3) -> 4 | C3: Not captured | D3: 4 | E3: =COUNTIFS('Feature Inventory'!B:B,A3,'Feature Inventory'!G:G,"Must") -> 4 | F3: =COUNTIFS('Feature Inventory'!B:B,A3,'Feature Inventory'!G:G,"Should") -> 0 | G3: =COUNTIFS('Feature Inventory'!B:B,A3,'Feature Inventory'!G:G,"Could") -> 0 | H3: =COUNTIFS('Feature Inventory'!B:B,A3,'Feature Inventory'!F:F,"1") -> 4 | I3: =COUNTIFS('Feature Inventory'!B:B,A3,'Feature Inventory'!F:F,"2") -> 0 | J3: =COUNTIFS('Feature Inventory'!B:B,A3,'Feature Inventory'!F:F,"3") -> 0 | K3: =COUNTIFS('Feature Inventory'!B:B,A3,'Feature Inventory'!H:H,"S") -> 0 | L3: =COUNTIFS('Feature Inventory'!B:B,A3,'Feature Inventory'!H:H,"M") -> 2 | M3: =COUNTIFS('Feature Inventory'!B:B,A3,'Feature Inventory'!H:H,"L") -> 2
A4: Module 2 - Technical Change | B4: =COUNTIF('Feature Inventory'!B:B,A4) -> 41 | C4: Not captured | D4: 0 | E4: =COUNTIFS('Feature Inventory'!B:B,A4,'Feature Inventory'!G:G,"Must") -> 28 | F4: =COUNTIFS('Feature Inventory'!B:B,A4,'Feature Inventory'!G:G,"Should") -> 11 | G4: =COUNTIFS('Feature Inventory'!B:B,A4,'Feature Inventory'!G:G,"Could") -> 2 | H4: =COUNTIFS('Feature Inventory'!B:B,A4,'Feature Inventory'!F:F,"1") -> 0 | I4: =COUNTIFS('Feature Inventory'!B:B,A4,'Feature Inventory'!F:F,"2") -> 39 | J4: =COUNTIFS('Feature Inventory'!B:B,A4,'Feature Inventory'!F:F,"3") -> 2 | K4: =COUNTIFS('Feature Inventory'!B:B,A4,'Feature Inventory'!H:H,"S") -> 6 | L4: =COUNTIFS('Feature Inventory'!B:B,A4,'Feature Inventory'!H:H,"M") -> 26 | M4: =COUNTIFS('Feature Inventory'!B:B,A4,'Feature Inventory'!H:H,"L") -> 9
A5: Module 3 - SRM | B5: =COUNTIF('Feature Inventory'!B:B,A5) -> 46 | C5: Not captured | D5: 0 | E5: =COUNTIFS('Feature Inventory'!B:B,A5,'Feature Inventory'!G:G,"Must") -> 33 | F5: =COUNTIFS('Feature Inventory'!B:B,A5,'Feature Inventory'!G:G,"Should") -> 10 | G5: =COUNTIFS('Feature Inventory'!B:B,A5,'Feature Inventory'!G:G,"Could") -> 3 | H5: =COUNTIFS('Feature Inventory'!B:B,A5,'Feature Inventory'!F:F,"1") -> 42 | I5: =COUNTIFS('Feature Inventory'!B:B,A5,'Feature Inventory'!F:F,"2") -> 0 | J5: =COUNTIFS('Feature Inventory'!B:B,A5,'Feature Inventory'!F:F,"3") -> 4 | K5: =COUNTIFS('Feature Inventory'!B:B,A5,'Feature Inventory'!H:H,"S") -> 7 | L5: =COUNTIFS('Feature Inventory'!B:B,A5,'Feature Inventory'!H:H,"M") -> 23 | M5: =COUNTIFS('Feature Inventory'!B:B,A5,'Feature Inventory'!H:H,"L") -> 16
A6: Cross-Cutting Platform | B6: =COUNTIF('Feature Inventory'!B:B,A6) -> 17 | C6: Not captured | D6: 0 | E6: =COUNTIFS('Feature Inventory'!B:B,A6,'Feature Inventory'!G:G,"Must") -> 16 | F6: =COUNTIFS('Feature Inventory'!B:B,A6,'Feature Inventory'!G:G,"Should") -> 0 | G6: =COUNTIFS('Feature Inventory'!B:B,A6,'Feature Inventory'!G:G,"Could") -> 1 | H6: =COUNTIFS('Feature Inventory'!B:B,A6,'Feature Inventory'!F:F,"1") -> 15 | I6: =COUNTIFS('Feature Inventory'!B:B,A6,'Feature Inventory'!F:F,"2") -> 0 | J6: =COUNTIFS('Feature Inventory'!B:B,A6,'Feature Inventory'!F:F,"3") -> 2 | K6: =COUNTIFS('Feature Inventory'!B:B,A6,'Feature Inventory'!H:H,"S") -> 1 | L6: =COUNTIFS('Feature Inventory'!B:B,A6,'Feature Inventory'!H:H,"M") -> 8 | M6: =COUNTIFS('Feature Inventory'!B:B,A6,'Feature Inventory'!H:H,"L") -> 8
A7: Total | B7: =SUM(B2:B6) -> 148 | C7: =SUM(C2:C6) -> 0 | D7: =SUM(D2:D6) -> 9 | E7: =SUM(E2:E6) -> 113 | F7: =SUM(F2:F6) -> 27 | G7: =SUM(G2:G6) -> 8 | H7: =SUM(H2:H6) -> 100 | I7: =SUM(I2:I6) -> 39 | ... M7: =SUM(M2:M6) -> 47

Sheet Legend
A1: Column | B1: Meaning
A2: Feature ID | B2: Unique sequential reference (F-001, F-002...)
A3: Module | B3: Platform module the feature belongs to (colour-coded, matching Summary sheet)
A4: Stage | B4: The workflow stage this feature sits in (per the three approved workflow visuals)
A5: Feature | B5: Short feature name, exactly as it appears in the Deep-Dive Feature Specification v0.2
A6: What It Does | B6: One-line functional description
A7: Status | B7: Confirmed FR = traceable to an original Functional Requirement (BRD v0.1). ★ Newly Surfaced = named in the workflow visuals but not in the original 50 FRs — needs a scope/priority decision
A8: FR Ref | B8: Functional Requirement number(s) this feature maps to, where applicable
A9: Open Item Ref | B9: Cross-reference to the Estimation Risk Register (#1–#11) in the BRD / Deep-Dive doc, where this feature carries an open question
A10: Phase | B10: 1 = Core Go-Live, 2 = Technical Change optional package, 3 = Advanced AI/Forecasting
A11: Priority (MoSCoW) | B11: Must / Should / Could. Confirmed FR items default to Must; newly-surfaced items are Should unless they are pure AI/analytics add-ons (Could). Review before finalising.
A12: Complexity (S/M/L) | B12: Small / Medium / Large — a relative sizing input for the estimator, assigned heuristically from feature type (data tree, AI/extraction, and mass-upload features trend Large; simple CRUD/master fields trend Small). Re-validate for anything estimation-critical.
A14: Effort Estimate (Person-Days)
A15: Architect Notes | B15: Free-text field for architects to record assumptions, dependencies, or design notes affecting the effort estimate.
A16: Note: Priority and Complexity are heuristic starting points generated for this inventory, not confirmed estimates — validate with the delivery team, especially for every ★ Newly Surfaced and every row carrying an Open Item Ref.

Sheet Review Summary
A1: SAVWIPL AIS – Feature Inventory & Effort Review
A2: Review of procurement digitalisation, technical change evaluation, SRM and cross-cutting platform work. Estimates are normalized to 8-hour person-days.
A4: Inventory Quality | B4: Value | C4: Finding | D4: Action
A5: Rows reviewed | B5: 150 | C5: 148 numbered features + 2 unnumbered rows | D5: Retain one consistent WBS numbering scheme
A6: Original manual effort (normalized PD) | B6: 1234 | C6: Computed from 9,872 hours | D6: Use hours as current source of truth
A7: Original Claude effort (normalized PD) | B7: 820 | C7: Computed from 6,560 hours | D7: Current saving assumption is aggressive
A8: Current implied Claude saving | B8: 0.33549433 | C8: Across listed feature hours | D8: Revalidate by work type and SDLC role
A9: Recommended feature manual effort (most likely PD) | B9: 1965 | C9: Feature-level re-baseline | D9: Still excludes de-duplicated project-level gaps
A10: Recommended feature Claude effort (most likely PD) | B10: 1598 | C10: Enterprise-lifecycle-aware AI benefit | D10: Use as planning baseline, not commitment
A11: Coverage gap work packages | B11: 63 | C11: Missing, partial or clarification items | D11: Add/decompose before commercial submission
A12: Summary formula issue | B12: 2 | C12: Original Summary has broken C/D formulas | D12: Add traceability columns or use Review Summary
A15: Module | B15: Current Manual PD | C15: Current Claude PD | D15: Reviewed Manual PD | E15: Reviewed Claude PD
A16: Module 1 - Procurement | B16: 340 | C16: 213 | D16: 565 | E16: 446
A17: Procurement Orders | B17: 34 | C17: 23 | D17: 41 | E17: 31
A18: Module 2 - Technical Change | B18: 294 | C18: 197 | D18: 455 | E18: 368
A19: Module 3 - SRM | B19: 301 | C19: 185 | D19: 410 | E19: 323
A20: Cross-Cutting Platform | B20: 235 | C20: 180 | D20: 494 | E20: 430
A21: Unassigned | B21: 30 | C21: 22 | D21: 0 | E21: 0
A24: Assessment | B24: Count | C24: Current Manual PD | D24: Reviewed Manual PD
A25: Underestimated | B25: 35 | C25: 394 | D25: 759
A26: Broadly reasonable | B26: 86 | C26: 499 | D26: 633
A27: Scope confirmation required | B27: 9 | C27: 62 | D27: 74
A28: Shared-enabler boundary required | B28: 17 | C28: 235 | D28: 494
A29: Potential overlap / overestimate | B29: 1 | C29: 14 | D29: 5
A30: Merge / remove from total | B30: 2 | C30: 30 | D30: 0
A33: Critical Review Findings | F33: Gap Category | G33: Items | H33: Manual Low | I33: Manual Most Likely | J33: Claude Most Likely
A34: # | B34: Issue | C34: Evidence | D34: Recommended Action | F34: Discovery & Governance | G34: 10 | H34: 249 | I34: 335 | J34: 271
A35: 1 | B35: Duplicate unnumbered rows | C35: Authentication & Authorization overlaps F-129; Notification Module overlaps F-026/F-126/F-130/F-146. | D35: Remove from totals or retain only as non-estimated epic headings. | F35: Platform Administration | G35: 9 | H35: 118 | I35: 171 | J35: 137
A36: 2 | B36: Mixed WBS levels | C36: The inventory mixes epics, shared engines, integrations, screens, business rules and delivery activities. | D36: Add WBS Level, Parent Feature and Estimate Boundary columns. | F36: Data & Integration | G36: 8 | H36: 141 | I36: 196 | J36: 171
A37: 3 | B37: Broken traceability | C37: Legend describes Status, FR Ref and Open Item Ref, but those columns are absent; Summary formulas consequently fail. | D37: Add an RFQ-to-feature traceability matrix before bid submission. | F37: Procurement Rules | G37: 5 | H37: 41 | I37: 61 | J37: 45
A38: 4 | B38: Scope expansion risk | C38: F-007 to F-011 and F-037 to F-040 are not clearly explicit in the RFQ baseline. | D38: Confirm as in-scope, optional or future phase. | F38: Technical Change Rules | G38: 4 | H38: 31 | I38: 46 | J38: 37
A39: 5 | B39: Shared-platform double count | C39: F-124 to F-130 and F-143 to F-146 can overlap with module-level tasks. | D39: Estimate foundation once; module rows should cover configuration/incremental effort. | F39: SRM Rules | G39: 4 | H39: 31 | I39: 46 | J39: 35
A40: 6 | B40: AI duplication | C40: F-117 and F-123 overlap; F-128 also overlaps all module chatbots. | D40: Use one shared AI platform plus module-specific intents, schemas and test packs. | F40: AI Governance & MLOps | G40: 7 | H40: 139 | I40: 193 | J40: 166
A41: 7 | B41: Estimate conversion errors | C41: Rows 2–3 contain hours without days; F-145 shows 12 days/160 hours and 10 AI days/120 hours. | D41: Standardize on 8-hour days and formula-driven hour/day conversion. | F41: Quality & Non-Functional | G41: 7 | H41: 182 | I41: 245 | J41: 211
A42: 8 | B42: Full-project work absent | C42: BRD, UX, architecture, QA, performance, security, migration, DevOps, training delivery, cutover and support setup are not consistently estimated. | D42: Add the Coverage Gaps work packages and re-baseline. | F42: DevOps & Operations | G42: 4 | H42: 71 | I42: 100 | J42: 88
A43: 9 | B43: AI saving assumption | C43: Current hours imply 33.6% saving, including work that is not strongly AI-compressible. | D43: Apply AI factors by task type; validate with historical delivery data. | F43: Training & Go-Live | G43: 5 | H43: 78 | I43: 110 | J43: 101
A44: 10 | B44: Four-month timeline | C44: The current list represents 100 Phase-1 features before missing delivery tasks are considered. | D44: Deliver a prioritized MVP and run parallel workstreams; do not promise all advanced AI and integrations in one release.

Sheet Feature Estimate Review
A1: Source Row | B1: Feature ID | C1: Module | D1: Stage | E1: Feature | F1: Phase | G1: Priority | H1: Complexity | I1: Current Manual PD (Normalized from Hours) | J1: Current Claude AI PD (Normalized from Hours) | K1: Estimate Category | L1: Assessment | M1: Recommended Manual PD - Low | N1: Recommended Manual PD - Most Likely | O1: Recommended Manual PD - High | P1: Recommended Claude AI PD - Most Likely | Q1: Confidence | R1: Review Rationale
A2: 2 | B2: UNNUMBERED | C2: Unassigned | D2: Unassigned | E2: Authentication & Authorization | F2: 1 | H2: S | I2: ='Feature Inventory'!J2/8 -> 10 | J2: ='Feature Inventory'!L2/8 -> 7 | K2: Duplicate / unnumbered | L2: Merge / remove from total | M2: 0 | N2: 0 | O2: 0 | P2: 0 | Q2: High | R2: Unnumbered and overlaps with cross-cutting Security/Access and Notification/Task Centre features; retain only as epic headings.
A3: 3 | B3: UNNUMBERED | C3: Unassigned | D3: Unassigned | E3: Notification Module | F3: 1 | H3: L | I3: ='Feature Inventory'!J3/8 -> 20 | J3: ='Feature Inventory'!L3/8 -> 15 | K3: Duplicate / unnumbered | L3: Merge / remove from total | M3: 0 | N3: 0 | O3: 0 | P3: 0 | Q3: High | R3: Unnumbered and overlaps with cross-cutting Security/Access and Notification/Task Centre features; retain only as epic headings.
A4: 4 | B4: F-001 | C4: Module 1 - Procurement | D4: Define & Plan | E4: Create Project | F4: 1 | G4: Must | H4: M | I4: ='Feature Inventory'!J4/8 -> 5 | J4: ='Feature Inventory'!L4/8 -> 3 | K4: CRUD / configuration | L4: Broadly reasonable | M4: 4 | N4: 6 | O4: 7 | P4: 4 | Q4: Medium | R4: Reasonable as a build estimate, subject to confirmed acceptance criteria, data volumes and shared-platform assumptions.
A5: 5 | B5: F-002 | C5: Module 1 - Procurement | D5: Define & Plan | E5: Upload BOM & Part List | F5: 1 | G5: Must | H5: L | I5: ='Feature Inventory'!J5/8 -> 12 | J5: ='Feature Inventory'!L5/8 -> 7 | K5: Data ingestion / migration | L5: Underestimated | M5: 15 | N5: 19 | O5: 25 | P5: 15 | Q5: Medium | R5: Current estimate does not fully reflect enterprise validation, error handling, integration, security, audit and test effort.
A6: 6 | B6: F-003 | C6: Module 1 - Procurement | D6: Define & Plan | E6: Maintain Master Data (Project, Part, Supplier, Commodity, FX) | F6: 1 | G6: Must | H6: L | I6: ='Feature Inventory'!J6/8 -> 15 | J6: ='Feature Inventory'!L6/8 -> 8 | K6: Complex data / calculation | L6: Broadly reasonable | M6: 18 | N6: 22 | O6: 30 | P6: 17 | Q6: Medium | R6: Reasonable as a build estimate, subject to confirmed acceptance criteria, data volumes and shared-platform assumptions.
A7: 7 | B7: F-004 | C7: Module 1 - Procurement | D7: Define & Plan | E7: Define Commodity & Exchange Rate | F7: 1 | G7: Must | H7: M | I7: ='Feature Inventory'!J7/8 -> 6 | J7: ='Feature Inventory'!L7/8 -> 3 | K7: Complex data / calculation | L7: Underestimated | M7: 7 | N7: 9 | O7: 12 | P7: 7 | Q7: Medium | R7: Current estimate does not fully reflect enterprise validation, error handling, integration, security, audit and test effort.
A8: 8 | B8: F-005 | C8: Module 1 - Procurement | D8: Define & Plan | E8: Define Milestones & Targets | F8: 1 | G8: Must | H8: L | I8: ='Feature Inventory'!J8/8 -> 10 | J8: ='Feature Inventory'!L8/8 -> 7 | K8: CRUD / configuration | L8: Broadly reasonable | M8: 9 | N8: 11 | O8: 14 | P8: 8 | Q8: Medium | R8: Reasonable as a build estimate, subject to confirmed acceptance criteria, data volumes and shared-platform assumptions.
A9: 9 | B9: F-006 | C9: Module 1 - Procurement | D9: Source & Nominate | E9: Import Sourcing Report (EBON+) | F9: 1 | G9: Must | H9: L | I9: ='Feature Inventory'!J9/8 -> 18 | J9: ='Feature Inventory'!L9/8 -> 11 | K9: External integration | L9: Underestimated | M9: 28 | N9: 36 | O9: 48 | P9: 28 | Q9: Medium | R9: Current estimate does not fully reflect enterprise validation, error handling, integration, security, audit and test effort.
A10: 10 | B10: F-007 | C10: Module 1 - Procurement | D10: Source & Nominate | E10: RFQ Management | F10: 1 | G10: Should | H10: M | I10: ='Feature Inventory'!J10/8 -> 7 | J10: ='Feature Inventory'!L10/8 -> 5 | K10: Scope clarification | L10: Scope confirmation required | M10: 7 | N10: 8 | O10: 11 | P10: 6 | Q10: Low | R10: Not clearly stated in the RFQ baseline; include only after customer confirmation or treat as optional enhancement.
A11: 11 | B11: F-008 | C11: Module 1 - Procurement | D11: Source & Nominate | E11: Supplier Quotations | F11: 1 | G11: Should | H11: M | I11: ='Feature Inventory'!J11/8 -> 6 | J11: ='Feature Inventory'!L11/8 -> 4 | K11: Scope clarification | L11: Scope confirmation required | M11: 6 | N11: 7 | O11: 10 | P11: 5 | Q11: Low | R11: Not clearly stated in the RFQ baseline; include only after customer confirmation or treat as optional enhancement.
A12: 12 | B12: F-009 | C12: Module 1 - Procurement | D12: Source & Nominate | E12: Supplier Comparison | F12: 1 | G12: Should | H12: S | I12: ='Feature Inventory'!J12/8 -> 4 | J12: ='Feature Inventory'!L12/8 -> 2 | K12: Scope clarification | L12: Scope confirmation required | M12: 4 | N12: 5 | O12: 6 | P12: 4 | Q12: Low | R12: Not clearly stated in the RFQ baseline; include only after customer confirmation or treat as optional enhancement.
A13: 13 | B13: F-010 | C13: Module 1 - Procurement | D13: Source & Nominate | E13: Supplier Nomination | F13: 1 | G13: Must | H13: M | I13: ='Feature Inventory'!J13/8 -> 5 | J13: ='Feature Inventory'!L13/8 -> 3 | K13: Scope clarification | L13: Scope confirmation required | M13: 5 | N13: 6 | O13: 8 | P13: 5 | Q13: Low | R13: Not clearly stated in the RFQ baseline; include only after customer confirmation or treat as optional enhancement.
A14: 14 | B14: F-011 | C14: Module 1 - Procurement | D14: Source & Nominate | E14: Commercial Negotiation | F14: 1 | G14: Must | H14: M | I14: ='Feature Inventory'!J14/8 -> 6 | J14: ='Feature Inventory'!L14/8 -> 4 | K14: Scope clarification | L14: Scope confirmation required | M14: 6 | N14: 7 | O14: 10 | P14: 5 | Q14: Low | R14: Not clearly stated in the RFQ baseline; include only after customer confirmation or treat as optional enhancement.
A15: 15 | B15: F-012 | C15: Module 1 - Procurement | D15: Commercial Management | E15: Cost Breakdown (CBD) | F15: 1 | G15: Must | H15: L | I15: ='Feature Inventory'!J15/8 -> 18 | J15: ='Feature Inventory'!L15/8 -> 13 | K15: Complex data / calculation | L15: Underestimated | M15: 32 | N15: 42 | O15: 56 | P15: 33 | Q15: Medium | R15: Current estimate does not fully reflect enterprise validation, error handling, integration, security, audit and test effort.
... A151: 151 | B151: F-148 | C151: Cross-Cutting Platform | D151: Platform Services | E151: Annual AI / Software Version Upgrade | F151: 3 | G151: Must | H151: M | I151: ='Feature Inventory'!J151/8 -> 5 | J151: ='Feature Inventory'!L151/8 -> 5 | K151: AI / ML / Intelligent automation | L151: Shared-enabler boundary required | M151: 8 | N151: 10 | O151: 15 | P151: 10 | Q151: Medium | R151: Valid shared platform work, but module rows must be estimated as incremental configuration to avoid double counting.

Sheet Coverage Gaps
A1: Gap ID | B1: Category | C1: Work Package / Missing Task | D1: Coverage Status | E1: Source / Requirement Reference | F1: Manual PD - Low | G1: Manual PD - Most Likely | H1: Manual PD - High | I1: Claude AI PD - Most Likely | J1: Estimate Handling | K1: Review Note
A2: G-001 | B2: Discovery & Governance | C2: BRD preparation, workshops and customer approval | D2: Requirement | E2: RFQ Requirements + Statistics rows 47-49 | F2: 30 | G2: 40 | H2: 55 | I2: 32 | J2: Add as explicit project work package | K2: Required for full-project delivery but absent from the current feature inventory.
A3: G-002 | B3: Discovery & Governance | C3: Requirement traceability matrix (RFQ row-to-feature-to-test mapping) | D3: Requirement | E3: Needed for bid and scope control | F3: 8 | G3: 10 | H3: 14 | I3: 7 | J3: Add as explicit project work package | K3: Required for full-project delivery but absent from the current feature inventory.
A4: G-003 | B4: Discovery & Governance | C4: Detailed functional design, user stories and acceptance criteria | D4: Design | E4: All modules | F4: 25 | G4: 35 | H4: 50 | I4: 25 | J4: Add as explicit project work package | K4: Required for full-project delivery but absent from the current feature inventory.
A5: G-004 | B5: Discovery & Governance | C5: UX/UI research, wireframes, design system and responsive prototypes | D5: Design | E5: Laptop/iPad/mobile scope | F5: 32 | G5: 45 | H5: 60 | I5: 32 | J5: Add as explicit project work package | K5: Required for full-project delivery but absent from the current feature inventory.
A6: G-005 | B6: Discovery & Governance | C6: Solution architecture and deployment topology | D6: Design | E6: Technical Solution Document architecture dependency | F6: 18 | G6: 25 | H6: 35 | I6: 20 | J6: Add as explicit project work package | K6: Required for full-project delivery but absent from the current feature inventory.
A7: G-006 | B7: Discovery & Governance | C7: Data architecture, logical/physical model, data dictionary and governance | D7: Design | E7: Central governed repository | F7: 22 | G7: 30 | H7: 45 | I7: 24 | J7: Add as explicit project work package | K7: Required for full-project delivery but absent from the current feature inventory.
A8: G-007 | B8: Discovery & Governance | C8: Integration assessment, interface contracts and API/file specifications | D8: Design | E8: EBON/SAP/email/market data | F8: 15 | G8: 20 | H8: 30 | I8: 16 | J8: Add as explicit project work package | K8: Required for full-project delivery but absent from the current feature inventory.
A9: G-008 | B9: Discovery & Governance | C9: Annexure A security compliance assessment and control matrix | D9: Design | E9: RFQ Requirements + Statistics row 53 | F9: 24 | G9: 30 | H9: 45 | I9: 27 | J9: Add as explicit project work package | K9: Required for full-project delivery but absent from the current feature inventory.
A10: G-009 | B10: Discovery & Governance | C10: Project management, Agile ceremonies, RAID, status and stakeholder governance | D10: PM | E10: RFQ prefers Agile delivery | F10: 60 | G10: 80 | H10: 100 | I10: 70 | J10: Add as explicit project work package | K10: Required for full-project delivery but absent from the current feature inventory.
A11: G-010 | B11: Discovery & Governance | C11: Business change management and stakeholder communication plan | D11: PM | E11: Enterprise adoption | F11: 15 | G11: 20 | H11: 30 | I11: 18 | J11: Add as explicit project work package | K11: Required for full-project delivery but absent from the current feature inventory.
A12: G-011 | B12: Platform Administration | C12: User/role/permission matrix and user administration screens | D12: Requirement | E12: F-129 covers security but not detailed admin UX | F12: 10 | G12: 15 | H12: 22 | I12: 12 | J12: Decompose/replace related feature; do not simply add | K12: The capability is implied by an existing feature, but the delivery work and acceptance criteria are not visible.
A13: G-012 | B13: Platform Administration | C13: Workflow configuration and approval-matrix administration | D13: Assumption | E13: F-125 shared workflow engine | F13: 14 | G13: 20 | H13: 30 | I13: 16 | J13: Decompose/replace related feature; do not simply add | K13: The capability is implied by an existing feature, but the delivery work and acceptance criteria are not visible.
... A64: G-063 | B64: Training & Go-Live | C64: 10x5 support model, SLA, incident/problem/change process and service desk setup | D64: Support | E64: RFQ rows 57-60 | F64: 14 | G64: 20 | H64: 30 | I64: 19 | J64: Add as explicit project work package | K64: Required for full-project delivery but absent from the current feature inventory.

Sheet Estimate Assumptions
A1: SAVWIPL AIS – Estimate Review Assumptions & Boundaries
A3: Topic | B3: Review Assumption / Guidance
A4: Working Day | B4: 1 person-day = 8 person-hours. The workbook has missing day values in rows 2–3 and an hour/day mismatch for F-145, so review totals are normalized from hours.
A5: Current Estimate Boundary | B5: The existing estimates appear to be feature-build estimates. They do not consistently show BRD, UX, architecture, QA, security, migration, DevOps, project management, training delivery, cutover or support setup.
A6: Recommended Feature Estimate | B6: Most-likely feature estimates include solution/detail design for the feature, development/configuration, code review, unit testing, developer integration testing and technical documentation.
A7: Project-Level Work | B7: Coverage Gaps contains delivery work packages that must be planned separately or explicitly decomposed from shared epics. Do not add all 'Partially covered' items without removing overlap.
A8: Claude AI Assistance | B8: Assumes enterprise use of Claude for analysis, code assistance, test generation and documentation. It does not materially reduce customer approvals, environment access, data cleansing, integration coordination, UAT or production support.
A9: AI Saving Expectation | B9: The current workbook implies approximately 33.6% saving. For the full enterprise lifecycle, a planning range of roughly 18–28% is more defensible until team maturity and reusable accelerators are demonstrated.
A10: Scope Boundary | B10: RFQ Management, Supplier Quotations/Comparison/Negotiation/Nomination and the separate Procurement Orders block are not clearly explicit in the RFQ baseline and should be confirmed as optional or included scope.
A11: Shared Enablers | B11: Master Data Core, Workflow Engine, Dashboards, AI Assistant, Notifications and Security are valid shared components. Module-level rows must represent incremental configuration, not a second full build.
A12: Estimate Confidence | B12: High = duplicate/error can be objectively identified. Medium = reasonable architectural estimate with open data/integration details. Low = scope or operating model is not confirmed.
A13: Contingency | B13: After BRD and technical discovery, apply 15–25% contingency to low-confidence integrations, AI/forecasting, migration, security and on-prem infrastructure items.
A14: Timeline | B14: A four-month go-live is feasible only as a tightly governed phased MVP with parallel workstreams, early infrastructure access, fixed templates, limited integration uncertainty and rapid customer sign-off.
